{
    "container": {
        "height": 500,
        "width": 800
    },
    "blocks": [
        {
            "top": 47,
            "left": 330,
            "componentKey": "button",
            "adjustPosition": false,
            "focus": false,
            "zIndex": 0,
            "width": 70,
            "height": 40,
            "hasResize": false,
            "props": {},
            "model": {},
            "slotName": "subBtn"
        },
        {
            "top": 125,
            "left": 115,
            "componentKey": "text",
            "adjustPosition": false,
            "focus": false,
            "zIndex": 0,
            "width": 80,
            "height": 28,
            "hasResize": false,
            "props": {},
            "model": {}
        },
        {
            "top": 241,
            "left": 63.5,
            "componentKey": "select",
            "adjustPosition": false,
            "focus": false,
            "zIndex": 0,
            "width": 193,
            "height": 40,
            "hasResize": false,
            "props": {},
            "model": {}
        },
        {
            "top": 241,
            "left": 330,
            "componentKey": "select",
            "adjustPosition": false,
            "focus": true,
            "zIndex": 0,
            "width": 193,
            "height": 40,
            "hasResize": false,
            "props": {
                "options": [
                    {
                        "label": "蛋糕",
                        "value": "dangao",
                        "comments": "钱二分"
                    },
                    {
                        "label": "雪碧",
                        "value": "xuebi",
                        "comments": "啊啊女"
                    }
                ]
            },
            "model": {
                "default": "food"
            }
        },
        {
            "top": 100,
            "left": 529.5,
            "componentKey": "number-range",
            "adjustPosition": false,
            "focus": false,
            "zIndex": 0,
            "width": 225,
            "height": 40,
            "hasResize": false,
            "props": {},
            "model": {
                "start": "testStart",
                "end": "testEnd"
            }
        }
    ]
}